networking_cisco/__init__.py
networking_cisco/_i18n.py
networking_cisco/agent/__init__.py
networking_cisco/agent/aci_topology.py
networking_cisco/agent/agent.py
networking_cisco/agent/lldp_topology.py
networking_cisco/agent/nxos_topology.py
networking_cisco/apps/__init__.py
networking_cisco/apps/saf/__init__.py
networking_cisco/apps/saf/dfa_cli.py
networking_cisco/apps/saf/dfa_enabler_agent.py
networking_cisco/apps/saf/dfa_enabler_server.py
networking_cisco/apps/saf/agent/__init__.py
networking_cisco/apps/saf/agent/detect_uplink.py
networking_cisco/apps/saf/agent/dfa_agent.py
networking_cisco/apps/saf/agent/iptables_driver.py
networking_cisco/apps/saf/agent/topo_disc/__init__.py
networking_cisco/apps/saf/agent/topo_disc/pub_lldp_api.py
networking_cisco/apps/saf/agent/topo_disc/topo_disc.py
networking_cisco/apps/saf/agent/topo_disc/topo_disc_constants.py
networking_cisco/apps/saf/agent/vdp/__init__.py
networking_cisco/apps/saf/agent/vdp/dfa_vdp_mgr.py
networking_cisco/apps/saf/agent/vdp/lldpad.py
networking_cisco/apps/saf/agent/vdp/lldpad_constants.py
networking_cisco/apps/saf/agent/vdp/ovs_vdp.py
networking_cisco/apps/saf/agent/vdp/vdp_constants.py
networking_cisco/apps/saf/common/__init__.py
networking_cisco/apps/saf/common/config.py
networking_cisco/apps/saf/common/constants.py
networking_cisco/apps/saf/common/dfa_exceptions.py
networking_cisco/apps/saf/common/dfa_logger.py
networking_cisco/apps/saf/common/dfa_sys_lib.py
networking_cisco/apps/saf/common/rpc.py
networking_cisco/apps/saf/common/utils.py
networking_cisco/apps/saf/db/__init__.py
networking_cisco/apps/saf/db/dfa_db_api.py
networking_cisco/apps/saf/db/dfa_db_models.py
networking_cisco/apps/saf/server/__init__.py
networking_cisco/apps/saf/server/cisco_dfa_rest.py
networking_cisco/apps/saf/server/dfa_events_handler.py
networking_cisco/apps/saf/server/dfa_fail_recovery.py
networking_cisco/apps/saf/server/dfa_instance_api.py
networking_cisco/apps/saf/server/dfa_listen_dcnm.py
networking_cisco-8.0.0.dist-info/AUTHORS
networking_cisco-8.0.0.dist-info/LICENSE
networking_cisco-8.0.0.dist-info/METADATA
networking_cisco-8.0.0.dist-info/WHEEL
networking_cisco-8.0.0.dist-info/entry_points.txt
networking_cisco-8.0.0.dist-info/pbr.json
networking_cisco-8.0.0.dist-info/top_level.txt
networking_cisco-8.0.0.dist-info/RECORD
