Metadata-Version: 2.1
Name: networking-cisco
Version: 8.0.0
Summary: Networking Cisco contains drivers for OpenStack Neutron to support Cisco equipment and products
Home-page: https://github.com/openstack/networking-cisco
Author: Cisco Systems
Author-email: openstack-networking@cisco.com
Classifier: Environment :: OpenStack
Classifier: Intended Audience :: Information Technology
Classifier: Intended Audience :: System Administrators
Classifier: License :: OSI Approved :: Apache Software License
Classifier: Operating System :: POSIX :: Linux
Classifier: Programming Language :: Python
Classifier: Programming Language :: Python :: 2
Classifier: Programming Language :: Python :: 2.7
Classifier: Programming Language :: Python :: 3.5
License-File: LICENSE
License-File: AUTHORS
Requires-Dist: pbr >=1.8
Requires-Dist: Babel >=1.3
Requires-Dist: ncclient >0.5.3
Requires-Dist: lxml >=3.3.3
Requires-Dist: oslo.config >=3.7.0
Requires-Dist: oslo.concurrency >=3.5.0
Requires-Dist: oslo.db >=4.1.0
Requires-Dist: oslo.i18n >=2.1.0
Requires-Dist: oslo.log >=1.14.0
Requires-Dist: oslo.messaging >=4.0.0
Requires-Dist: oslo.serialization >=1.10.0
Requires-Dist: oslo.service >=1.0.0
Requires-Dist: oslo.utils >=3.5.0
Requires-Dist: neutron >=20.3.1
Requires-Dist: neutron-lib >=3.4.0
Requires-Dist: python-neutronclient
Requires-Dist: pika >=0.10.0
Requires-Dist: ucsmsdk >=0.9.3.1
